pybabylonjs/__init__.py
pybabylonjs/_frontend.py
pybabylonjs/_version.py
pybabylonjs/args.py
pybabylonjs/babylonjs.py
pybabylonjs/data.py
pybabylonjs/show.py
pybabylonjs/labextension/package.json
pybabylonjs/labextension/static/453.5c80fd4abd99f4ec8535.js
pybabylonjs/labextension/static/470.37dfa364f96960352a7e.js
pybabylonjs/labextension/static/480.6a0376aafff506759369.js
pybabylonjs/labextension/static/501.2dc3a4ae6c2020e54579.js
pybabylonjs/labextension/static/56.4a91378b903c0a9ac293.js
pybabylonjs/labextension/static/568.28effd2c93b705b5fa72.js
pybabylonjs/labextension/static/578.e1e21eef85ed179b11d6.js
pybabylonjs/labextension/static/578.e1e21eef85ed179b11d6.js.LICENSE.txt
pybabylonjs/labextension/static/605.7fd11f4c843830ab8266.js
pybabylonjs/labextension/static/605.7fd11f4c843830ab8266.js.LICENSE.txt
pybabylonjs/labextension/static/627.5ca30d43e46a219d3da4.js
pybabylonjs/labextension/static/747.48c42efc0ad7ebdde4d6.js
pybabylonjs/labextension/static/779.2f0c25035dd562728e36.js
pybabylonjs/labextension/static/944.00ff1bac606f25cfdf91.js
pybabylonjs/labextension/static/944.00ff1bac606f25cfdf91.js.LICENSE.txt
pybabylonjs/labextension/static/remoteEntry.091199f12d20445240a1.js
pybabylonjs/labextension/static/style.js
pybabylonjs/labextension/static/third-party-licenses.json
pybabylonjs/nbextension/extension.js
pybabylonjs/nbextension/index.js
pybabylonjs/nbextension/index.js.map
pybabylonjs/tests/__init__.py
pybabylonjs/tests/conftest.py
pybabylonjs/tests/test_babylonjs.py
pybabylonjs/tests/test_nbextension_path.py
pybabylonjs-1.6.3.data/data/share/jupyter/labextensions/@tiledb-inc/pybabylonjs/install.json
pybabylonjs-1.6.3.data/data/share/jupyter/labextensions/@tiledb-inc/pybabylonjs/package.json
pybabylonjs-1.6.3.data/data/share/jupyter/labextensions/@tiledb-inc/pybabylonjs/static/453.5c80fd4abd99f4ec8535.js
pybabylonjs-1.6.3.data/data/share/jupyter/labextensions/@tiledb-inc/pybabylonjs/static/470.37dfa364f96960352a7e.js
pybabylonjs-1.6.3.dist-info/LICENSE
pybabylonjs-1.6.3.dist-info/METADATA
pybabylonjs-1.6.3.dist-info/WHEEL
pybabylonjs-1.6.3.dist-info/top_level.txt
pybabylonjs-1.6.3.dist-info/RECORD
