Metadata-Version: 2.1
Name: pybabylonjs
Version: 1.6.3
Summary: BabylonJS widget
Home-page: https://github.com/TileDB-Inc/TileDB-PyBabylonJS
Author: TileDB
Author-email: support@tiledb.com
License: MIT
Keywords: Jupyter,JupyterLab,JupyterLab3
Platform: Linux
Platform: Mac OS X
Platform: Windows
Classifier: License :: OSI Approved :: MIT License
Classifier: Programming Language :: Python
Classifier: Programming Language :: Python :: 3
Classifier: Programming Language :: Python :: 3.6
Classifier: Programming Language :: Python :: 3.7
Classifier: Programming Language :: Python :: 3.8
Classifier: Programming Language :: Python :: 3.9
Classifier: Framework :: Jupyter
Classifier: Framework :: Jupyter :: JupyterLab
Classifier: Framework :: Jupyter :: JupyterLab :: 3
Classifier: Framework :: Jupyter :: JupyterLab :: Extensions
Classifier: Framework :: Jupyter :: JupyterLab :: Extensions :: Prebuilt
Requires-Python: >=3.6
License-File: LICENSE
Requires-Dist: ipywidgets>=7
Provides-Extra: dev
Requires-Dist: matplotlib; extra == "dev"
Requires-Dist: python-pdal; extra == "dev"
Requires-Dist: pandas; extra == "dev"
Requires-Dist: cv2; extra == "dev"
